README
setup.py
Money/Currency.py
Money/Money.py
Money/__init__.py
pyMoney.egg-info/PKG-INFO
pyMoney.egg-info/SOURCES.txt
pyMoney.egg-info/dependency_links.txt
pyMoney.egg-info/top_level.txt