Metadata-Version: 1.0
Name: pyMoney
Version: 1.2.31
Summary: An implementation of a money type for Python 2.2 >
Home-page: http://github.com/srobertson/pyMoney
Author: Scott Robertson
Author-email: srobertson@codeit.com
License: Apache License 2.0
Platform: UNKNOWN
